space_bots/__init__.py
space_bots/battle_state.py
space_bots/entity.py
space_bots/force_utils.py
space_bots/game_engine_adapter.py
space_bots/planet.py
space_bots/squad.py
space_bots/universe.py
space_bots/images/Readme.md
space_bots/images/planet_brown.png
space_bots/ships/__init__.py
space_bots/ships/healer.py
space_bots/ships/miner.py
space_bots/ships/ship.py
space_bots/ships/ship_catalog.py
space_bots/ships/ship_parameters.py
space_bots/ships/ship_state.py
space_bots/ships/tank.py
space_bots-0.1.3.dist-info/LICENSE
space_bots-0.1.3.dist-info/METADATA
space_bots-0.1.3.dist-info/WHEEL
space_bots-0.1.3.dist-info/top_level.txt
space_bots-0.1.3.dist-info/RECORD
